AUTHORS
COPYING
LICENSE_appdirs.txt
README
babcom_cli
copyweb
fcpgenkey
fcpget
fcpgetdir
fcpinvertkey
fcpnames
fcpput
fcpputdir
fcpredirect
fcpupload
fproxyproxy
freesitemgr
pyNodeConfig
setup.cfg
setup.py
fcp3/__init__.py
fcp3/arguments.py
fcp3/fproxyproxy.py
fcp3/freenetfs.py
fcp3/genkey.py
fcp3/get.py
fcp3/invertkey.py
fcp3/names.py
fcp3/node.py
fcp3/pseudopythonparser.py
fcp3/put.py
fcp3/redirect.py
fcp3/sitemgr.py
fcp3/upload.py
fcp3/xmlobject.py
fcp3/xmlrpc.py
freenet3/__init__.py
freenet3/appdirs.py
freenet3/spawn.py
freenet_passlib_170/__init__.py
freenet_passlib_170/apache.py
freenet_passlib_170/apps.py
freenet_passlib_170/context.py
freenet_passlib_170/exc.py
freenet_passlib_170/hash.py
freenet_passlib_170/hosts.py
freenet_passlib_170/ifc.py
freenet_passlib_170/pwd.py
freenet_passlib_170/registry.py
freenet_passlib_170/totp.py
freenet_passlib_170/win32.py
freenet_passlib_170/_setup/__init__.py
freenet_passlib_170/_setup/docdist.py
freenet_passlib_170/_setup/stamp.py
freenet_passlib_170/crypto/__init__.py
freenet_passlib_170/crypto/_md4.py
freenet_passlib_170/crypto/des.py
freenet_passlib_170/crypto/digest.py
freenet_passlib_170/crypto/_blowfish/__init__.py
freenet_passlib_170/crypto/_blowfish/_gen_files.py
freenet_passlib_170/crypto/_blowfish/base.py
freenet_passlib_170/crypto/_blowfish/unrolled.py
freenet_passlib_170/crypto/scrypt/__init__.py
freenet_passlib_170/crypto/scrypt/_builtin.py
freenet_passlib_170/crypto/scrypt/_gen_files.py
freenet_passlib_170/crypto/scrypt/_salsa.py
freenet_passlib_170/ext/__init__.py
freenet_passlib_170/ext/django/__init__.py
freenet_passlib_170/ext/django/models.py
freenet_passlib_170/ext/django/utils.py
freenet_passlib_170/handlers/__init__.py
freenet_passlib_170/handlers/argon2.py
freenet_passlib_170/handlers/bcrypt.py
freenet_passlib_170/handlers/cisco.py
freenet_passlib_170/handlers/des_crypt.py
freenet_passlib_170/handlers/digests.py
freenet_passlib_170/handlers/django.py
freenet_passlib_170/handlers/fshp.py
pyFreenet3.egg-info/PKG-INFO
pyFreenet3.egg-info/SOURCES.txt
pyFreenet3.egg-info/dependency_links.txt
pyFreenet3.egg-info/top_level.txt