Metadata-Version: 2.1
Name: pyFreenet3
Version: 0.6.2
Summary: Freenet Client Protocol Helper
Home-page: http://127.0.0.1:8888/USK@~osOPnNLdMLVrYVNTahLufdwOuMhhC4GkpIHulnSm04,bwAmjkK-BZZnj-bujBQehwgGqUM1AUFhzTW4hcDGXQ0,AQACAAE/infocalypse_and_pyFreenet/5/
Author: Arne Babenhauserheide
Author-email: arne_bab@web.de
Classifier: Programming Language :: Python :: 3
Classifier: Development Status :: 4 - Beta
Classifier: Environment :: Other Environment
Classifier: Intended Audience :: Developers
Classifier: License :: OSI Approved :: GNU Lesser General Public License v2 or later (LGPLv2+)
Classifier: Operating System :: OS Independent
Classifier: Topic :: Software Development :: Libraries :: Python Modules
License-File: LICENSE_appdirs.txt
License-File: COPYING
License-File: AUTHORS
